ethereum_cli.py
ethereumd/__init__.py
ethereumd/poller.py
ethereumd/proxy.py
ethereumd/server.py
ethereumd/utils.py
ethereumd_proxy-0.3.0.dist-info/DESCRIPTION.rst
ethereumd_proxy-0.3.0.dist-info/LICENSE.txt
ethereumd_proxy-0.3.0.dist-info/METADATA
ethereumd_proxy-0.3.0.dist-info/RECORD
ethereumd_proxy-0.3.0.dist-info/WHEEL
ethereumd_proxy-0.3.0.dist-info/entry_points.txt
ethereumd_proxy-0.3.0.dist-info/metadata.json
ethereumd_proxy-0.3.0.dist-info/top_level.txt
tests/__init__.py
tests/base.py
tests/fakers.py
tests/test_poller.py
tests/test_proxy.py
tests/test_server.py
tests/test_utils.py
tests/box/Makefile
tests/box/block.sh
tests/box/ethereum.conf
tests/box/pswd.txt
tests/box/utils.js
tests/box/wallet.sh
tests/box/testnet/ethereum.conf
tests/box/testnet/history
tests/box/testnet/info.log
tests/box/testnet/geth/LOCK
tests/box/testnet/geth/nodekey
tests/box/testnet/geth/transactions.rlp
tests/box/testnet/geth/chaindata/000006.log
tests/box/testnet/geth/chaindata/000008.ldb
tests/box/testnet/geth/chaindata/CURRENT
tests/box/testnet/geth/chaindata/LOCK
tests/box/testnet/geth/chaindata/LOG
tests/box/testnet/geth/chaindata/MANIFEST-000007
tests/box/testnet/keystore/UTC--2017-10-01T01-14-42.178318382Z--98e681d7591b6b4cfba74a7792ac803a6dd49dd0
