Metadata-Version: 2.0
Name: ethereumd-proxy
Version: 0.3.0
Summary: Proxy client-server for Ethereum node using JSON-RPC interface.
Home-page: https://github.com/DeV1doR/ethereumd-proxy
Author: Bogdan Kurinnyi
Author-email: bogdankurinniy.dev1@gmail.com
License: MIT
Platform: UNKNOWN
Classifier: Development Status :: 4 - Beta
Classifier: Intended Audience :: Developers
Classifier: License :: OSI Approved :: MIT License
Classifier: Topic :: Software Development :: Libraries :: Python Modules
Classifier: Natural Language :: English
Classifier: Operating System :: OS Independent
Classifier: Programming Language :: Python :: 3.5
Classifier: Programming Language :: Python :: 3.6
Requires-Dist: sanic (==0.5.4)
Requires-Dist: aiohttp (==2.2.3)
Requires-Dist: APScheduler (==3.3.1)
Requires-Dist: colorlog (==2.10.0)
Requires-Dist: click (==6.7)
Requires-Dist: requests (==2.9.1)
Requires-Dist: ujson (==1.35)
Requires-Dist: aioethereum (==0.1.0)
